talkomatic/__init__.py
talkomatic/bot.py
talkomatic/api/__init__.py
talkomatic/api/v1/__init__.py
talkomatic/api/v1/api_key.py
talkomatic/api/v1/config.py
talkomatic/api/v1/emoji_list.py
talkomatic/api/v1/health.py
talkomatic/api/v1/me.py
talkomatic/api/v1/offensive_words.py
talkomatic/api/v1/rooms.py
talkomatic/commands/__init__.py
talkomatic/commands/command.py
talkomatic/dataclasses/__init__.py
talkomatic/dataclasses/rate_limits.py
talkomatic/dataclasses/room.py
talkomatic/dataclasses/user.py
talkomatic_py-0.1.1.dist-info/licenses/LICENSE
talkomatic_py-0.1.1.dist-info/METADATA
talkomatic_py-0.1.1.dist-info/WHEEL
talkomatic_py-0.1.1.dist-info/top_level.txt
talkomatic_py-0.1.1.dist-info/RECORD
