Metadata-Version: 2.4
Name: talkomatic.py
Version: 0.1.1
Summary: An easy-to-use Python versatile wrapper for the Talkomatic Bot interface ensuring best practices for making bots, and handling the REST API.
License-Expression: MIT
Project-URL: Documentation, https://batteraquette581.github.io/talkomatic.py-docs/
Project-URL: Homepage, https://github.com/BatteRaquette581/talkomatic.py/
Project-URL: Issues, https://github.com/BatteRaquette581/talkomatic.py/issues/
Classifier: Programming Language :: Python :: 3
Classifier: Programming Language :: Python :: 3.8
Classifier: Programming Language :: Python :: 3.9
Classifier: Programming Language :: Python :: 3.10
Classifier: Programming Language :: Python :: 3.11
Classifier: Programming Language :: Python :: 3.12
Classifier: Operating System :: OS Independent
Classifier: Intended Audience :: Developers
Classifier: Natural Language :: English
Classifier: Topic :: Internet
Classifier: Topic :: Software Development :: Libraries
Classifier: Topic :: Software Development :: Libraries :: Python Modules
Classifier: Topic :: Utilities
Classifier: Typing :: Typed
Classifier: Development Status :: 4 - Beta
Requires-Python: >=3.8
License-File: LICENSE
Requires-Dist: python-socketio
Requires-Dist: requests
Dynamic: license-file
